{"data":[{"id":1,"title":"{\"tr_TR\":\"Web & Mobile app  Designer\",\"ar\":\"\\u0628\\u0627\\u0644\\u0644\\u0630\\u0629\"}","subtitle":"{\"tr_TR\":\"Vacancy are available\",\"ar\":\"\\u0634\\u0627\\u063a\\u0631 \\u0645\\u062a\\u0627\\u062d\"}","image":"189","status":1,"created_at":"2022-11-07 04:47:10","updated_at":"2023-04-11 12:04:16"},{"id":2,"title":"{\"tr_TR\":\"Finance management\",\"ar\":\"\\u0628\\u0627\\u0644\\u0644\\u0630\\u0629\"}","subtitle":"{\"tr_TR\":\"Vacancy are available\",\"ar\":\"\\u0634\\u0627\\u063a\\u0631 \\u0645\\u062a\\u0627\\u062d\"}","image":"188","status":1,"created_at":"2022-11-07 04:48:17","updated_at":"2023-04-11 12:04:16"},{"id":3,"title":"{\"tr_TR\":\"Project management\",\"ar\":\"\\u0628\\u0627\\u0644\\u0644\\u0630\\u0629\"}","subtitle":"{\"tr_TR\":\"Vacancy are available\",\"ar\":\"\\u0634\\u0627\\u063a\\u0631 \\u0645\\u062a\\u0627\\u062d\"}","image":"187","status":1,"created_at":"2022-11-07 04:48:41","updated_at":"2023-04-11 12:04:16"},{"id":4,"title":"{\"tr_TR\":\"Human Research &amp; analysis\",\"ar\":\"\\u0628\\u0627\\u0644\\u0644\\u0630\\u0629\"}","subtitle":"{\"tr_TR\":\"Vacancy are available\",\"ar\":\"\\u0634\\u0627\\u063a\\u0631 \\u0645\\u062a\\u0627\\u062d\"}","image":"186","status":1,"created_at":"2022-11-07 04:49:13","updated_at":"2023-04-11 12:04:16"},{"id":5,"title":"{\"tr_TR\":\"Marketing &amp; Communication\",\"ar\":\"\\u0628\\u0627\\u0644\\u0644\\u0630\\u0629\"}","subtitle":"{\"tr_TR\":\"Vacancy are available\",\"ar\":\"\\u0634\\u0627\\u063a\\u0631 \\u0645\\u062a\\u0627\\u062d\"}","image":"185","status":1,"created_at":"2022-11-07 04:50:04","updated_at":"2023-04-11 12:04:16"},{"id":6,"title":"{\"tr_TR\":\"Customer care &amp; Support\",\"ar\":\"\\u0628\\u0627\\u0644\\u0644\\u0630\\u0629\"}","subtitle":"{\"tr_TR\":\"Vacancy are available\",\"ar\":\"\\u0634\\u0627\\u063a\\u0631 \\u0645\\u062a\\u0627\\u062d\"}","image":"184","status":1,"created_at":"2022-11-07 04:51:09","updated_at":"2023-04-11 12:04:16"},{"id":7,"title":"{\"tr_TR\":\"Digital Marketinng Consultant\",\"ar\":\"\\u0628\\u0627\\u0644\\u0644\\u0630\\u0629\"}","subtitle":"{\"tr_TR\":\"Vacancy are available\",\"ar\":\"\\u0634\\u0627\\u063a\\u0631 \\u0645\\u062a\\u0627\\u062d\"}","image":"183","status":1,"created_at":"2022-11-07 04:51:52","updated_at":"2023-04-11 12:04:16"},{"id":8,"title":"{\"tr_TR\":\"Web &amp; Mobile app  Developer\",\"ar\":\"\\u0628\\u0627\\u0644\\u0644\\u0630\\u0629\"}","subtitle":"{\"tr_TR\":\"Vacancy are available\",\"ar\":\"\\u0634\\u0627\\u063a\\u0631 \\u0645\\u062a\\u0627\\u062d\"}","image":"182","status":1,"created_at":"2022-11-07 04:52:30","updated_at":"2023-04-11 12:04:16"}]}